{
"type": "FeatureCollection",
"name": "geo_04_特定施設入居者生活介護（有料老人ホーム（サービス付き高齢者向け住宅））",
"crs": { "type": "name", "properties": { "name": "urn:ogc:def:crs:OGC:1.3:CRS84" } },
"features": [
{ "type": "Feature", "properties": { "内容": "アースサポートクオリア仙台高砂【特定施設入居者生活介護（有料老人ホーム（サービス付き高齢者向け住宅））】宮城県仙台市宮城野区福室3丁目24番18号", "url": "https://www.kaigokensaku.mhlw.go.jp/04/index.php?action_kouhyou_detail_004_kani=true&JigyosyoCd=475203162-00&ServiceCd=&Type=search", "url2": "http://www.earthsupport.co.jp" }, "geometry": { "type": "Point", "coordinates": [ 140.972981, 38.2824114 ] } },
{ "type": "Feature", "properties": { "内容": "特定施設入居者生活介護　ピーコムライフ鶴ケ谷【特定施設入居者生活介護（有料老人ホーム（サービス付き高齢者向け住宅））】宮城県仙台市宮城野区鶴ケ谷東1-1-5ピーコムライフ鶴ケ谷", "url": "https://www.kaigokensaku.mhlw.go.jp/04/index.php?action_kouhyou_detail_004_kani=true&JigyosyoCd=475202776-00&ServiceCd=&Type=search", "url2": "http://www.momotarousan.com/index.php" }, "geometry": { "type": "Point", "coordinates": [ 140.924886083466987, 38.288353388845302 ] } },
{ "type": "Feature", "properties": { "内容": "アースサポートクオリア仙台大和町【特定施設入居者生活介護（有料老人ホーム（サービス付き高齢者向け住宅））】宮城県仙台市若林区大和町5丁目30番25号", "url": "https://www.kaigokensaku.mhlw.go.jp/04/index.php?action_kouhyou_detail_004_kani=true&JigyosyoCd=475302113-00&ServiceCd=&Type=search", "url2": "http://www.earthsupport.co.jp" }, "geometry": { "type": "Point", "coordinates": [ 140.9243955, 38.2479253 ] } },
{ "type": "Feature", "properties": { "内容": "特定施設　第三白東苑【特定施設入居者生活介護（有料老人ホーム（サービス付き高齢者向け住宅））】宮城県仙台市太白区袋原4丁目35-35特定施設　第三白東苑", "url": "https://www.kaigokensaku.mhlw.go.jp/04/index.php?action_kouhyou_detail_004_kani=true&JigyosyoCd=475403267-00&ServiceCd=&Type=search", "url2": "https://sendai-venus.jp" }, "geometry": { "type": "Point", "coordinates": [ 140.915499944179999, 38.198607738904499 ] } },
{ "type": "Feature", "properties": { "内容": "サービス付き高齢者向け住宅こもれび（特定施設）【特定施設入居者生活介護（有料老人ホーム（サービス付き高齢者向け住宅））】宮城県仙台市泉区泉中央南１４番地", "url": "https://www.kaigokensaku.mhlw.go.jp/04/index.php?action_kouhyou_detail_004_kani=true&JigyosyoCd=475504056-00&ServiceCd=&Type=search", "url2": "http://www.tanpopoclinic.jp" }, "geometry": { "type": "Point", "coordinates": [ 140.8706225, 38.320281 ] } },
{ "type": "Feature", "properties": { "内容": "サービス付き高齢者住宅はなことば石巻【特定施設入居者生活介護（有料老人ホーム（サービス付き高齢者向け住宅））】宮城県石巻市駅前北通り一丁目14番21号", "url": "https://www.kaigokensaku.mhlw.go.jp/04/index.php?action_kouhyou_detail_004_kani=true&JigyosyoCd=470202771-00&ServiceCd=&Type=search", "url2": "https://hanakotoba.co.jp/facility/ishinomaki.html" }, "geometry": { "type": "Point", "coordinates": [ 141.3068441, 38.4381675 ] } },
{ "type": "Feature", "properties": { "内容": "暖暖の里角田【特定施設入居者生活介護（有料老人ホーム（サービス付き高齢者向け住宅））】宮城県角田市横倉字卯ノ崎94-17暖暖の里角田", "url": "https://www.kaigokensaku.mhlw.go.jp/04/index.php?action_kouhyou_detail_004_kani=true&JigyosyoCd=470800558-00&ServiceCd=&Type=search", "url2": "http://dandannosato.com/" }, "geometry": { "type": "Point", "coordinates": [ 140.7756862, 37.9892927 ] } },
{ "type": "Feature", "properties": { "内容": "シルバーランド　ドンクマサーかくだ【特定施設入居者生活介護（有料老人ホーム（サービス付き高齢者向け住宅））】宮城県角田市梶賀字東40番地1号", "url": "https://www.kaigokensaku.mhlw.go.jp/04/index.php?action_kouhyou_detail_004_kani=true&JigyosyoCd=470800525-00&ServiceCd=&Type=search", "url2": "http://www.dnkmsa.co.jp/" }, "geometry": { "type": "Point", "coordinates": [ 140.791645351590006, 37.988520726046701 ] } },
{ "type": "Feature", "properties": { "内容": "介護付き有料老人ホームルポたけくま【特定施設入居者生活介護（有料老人ホーム（サービス付き高齢者向け住宅））】宮城県岩沼市たけくま1丁目20番2号介護付き有料老人ホームルポたけくま", "url": "https://www.kaigokensaku.mhlw.go.jp/04/index.php?action_kouhyou_detail_004_kani=true&JigyosyoCd=471100503-00&ServiceCd=&Type=search", "url2": "http://www.well-nanten.jp/" }, "geometry": { "type": "Point", "coordinates": [ 140.860789, 38.1093646 ] } },
{ "type": "Feature", "properties": { "内容": "介護付き有料老人ホーム和笑の家【特定施設入居者生活介護（有料老人ホーム（サービス付き高齢者向け住宅））】宮城県大崎市大幡字新田81", "url": "https://www.kaigokensaku.mhlw.go.jp/04/index.php?action_kouhyou_detail_004_kani=true&JigyosyoCd=471502708-00&ServiceCd=&Type=search", "url2": "http://www.honoka-world.com" }, "geometry": { "type": "Point", "coordinates": [ 140.964659742296988, 38.5574938326492 ] } },
{ "type": "Feature", "properties": { "内容": "介護付有料老人ホーム　穂波あんしん館【特定施設入居者生活介護（有料老人ホーム（サービス付き高齢者向け住宅））】宮城県大崎市古川穂波三丁目７番５７号介護付有料老人ホーム　穂波あんしん館", "url": "https://www.kaigokensaku.mhlw.go.jp/04/index.php?action_kouhyou_detail_004_kani=true&JigyosyoCd=471502658-00&ServiceCd=&Type=search", "url2": "http://www.first-care.co.jp" }, "geometry": { "type": "Point", "coordinates": [ 140.9441933, 38.5613457 ] } }
]
}
